LICENCE
MANIFEST.in
README.md
setup.json
setup.py
aiida_python/__init__.py
aiida_python/calc.py
aiida_python/parser.py
aiida_python/serializers.py
aiida_python.egg-info/PKG-INFO
aiida_python.egg-info/SOURCES.txt
aiida_python.egg-info/dependency_links.txt
aiida_python.egg-info/entry_points.txt
aiida_python.egg-info/requires.txt
aiida_python.egg-info/top_level.txt
aiida_python/data/__init__.py
aiida_python/data/ihyh.py
tests/test_copyfile.py
tests/test_example.py
tests/test_exception.py
tests/test_serializers.py
tests/test_simple_code.py