Metadata-Version: 2.1
Name: aiida-python
Version: 0.0.6
Summary: AiiDA Python
Home-page: https://todo.nothing/
Author: Ot(t)o Kohulák
Author-email: otto.kohulak@dontemail.me
License: MIT
Classifier: Programming Language :: Python
Classifier: Intended Audience :: Science/Research
Classifier: License :: OSI Approved :: MIT License
Classifier: Natural Language :: English
Classifier: Framework :: AiiDA
License-File: LICENCE
Requires-Dist: aiida-core>=2.1.0
Provides-Extra: testing
Requires-Dist: pytest; extra == "testing"
Requires-Dist: pgtest; extra == "testing"
Requires-Dist: Pillow>=8.1.2; extra == "testing"
Provides-Extra: pre-commit
Requires-Dist: pre-commit~=2.2; extra == "pre-commit"
Requires-Dist: pylint<2.9,>=2.5.0; extra == "pre-commit"
Provides-Extra: docs
Requires-Dist: sphinx; extra == "docs"
Requires-Dist: sphinx-rtd-theme; extra == "docs"
